coolpandas/__init__.py
coolpandas/connect/__init__.py
coolpandas/connect/redshift.py
coolpandas/eda/__init__.py
coolpandas/eda/correlation.py
coolpandas/eda/distribution.py
coolpandas/eda/duplicates.py
coolpandas/eda/features_type.py
coolpandas/eda/geo_distance.py
coolpandas/eda/missing_values.py
coolpandas/eda/random_state.py
coolpandas/eda/shape.py
coolpandas/eda/summary.py
coolpandas/eda/value_counts.py
coolpandas/evaluate/__init__.py
coolpandas/evaluate/confusion_matrix.py
coolpandas/plot/__init__.py
coolpandas/plot/barplot.py
coolpandas/plot/boxplot.py
coolpandas/plot/confusion_matrix.py
coolpandas/plot/distplot.py
coolpandas/plot/geoplot.py
coolpandas/plot/lineplot.py
coolpandas/plot/mapplot.py
coolpandas/plot/scatterplot.py
coolpandas/plot/style.py
coolpandas/stats/__init__.py
coolpandas/stats/effect.py
coolpandas/stats/ttest.py
coolpandas/transform/__init__.py
coolpandas/transform/bin.py
coolpandas/transform/epoch.py
coolpandas/transform/missing_values.py
coolpandas/transform/outliers.py
coolpandas/utils/__init__.py
coolpandas/utils/random_state.py
coolpandas-0.4.7.dist-info/LICENSE
coolpandas-0.4.7.dist-info/METADATA
coolpandas-0.4.7.dist-info/WHEEL
coolpandas-0.4.7.dist-info/top_level.txt
coolpandas-0.4.7.dist-info/RECORD
