Metadata-Version: 2.1
Name: coolpandas
Version: 0.4.7
Summary: A Python package for Exploratory Data Analysis.
Author-email: Avel Docquin <adocquin@outlook.com>
Project-URL: Homepage, https://github.com/adocquin/coolpandas
Project-URL: Bug Tracker, https://github.com/adocquin/coolpandas/issues
Classifier: Development Status :: 3 - Alpha
Classifier: Intended Audience :: Developers
Classifier: Intended Audience :: Science/Research
Classifier: Programming Language :: Python :: 3
Classifier: Programming Language :: Python :: 3.10
Classifier: Programming Language :: Python :: 3.11
Classifier: License :: OSI Approved :: MIT License
Classifier: Operating System :: OS Independent
Classifier: Topic :: Scientific/Engineering :: Visualization
Requires-Python: >=3.10
License-File: LICENSE
Requires-Dist: pandas (>=2.0.3)
Requires-Dist: scipy (>=1.9.3)
Requires-Dist: scikit-learn (>=1.1.3)
Requires-Dist: plotly (>=5.15.0)
Requires-Dist: nbformat (>=5.7.0)
Requires-Dist: ipython (>=8.6.0)
Requires-Dist: openrouteservice (>=2.3.3)
Requires-Dist: redshift-connector (>=2.0.910)
Requires-Dist: statsmodels (>=0.14.0)
Requires-Dist: jinja2 (>=3.1.2)
Requires-Dist: pytest-cov (>=4.0.0)
Requires-Dist: black (>=22.10.0)
Requires-Dist: pylint (>=2.15.5)
Requires-Dist: isort (>=5.10.1)
Requires-Dist: pre-commit (>=2.20.0)
